{"name":"checkWindowCustomView","id":"testpackage.WhenCustomViewTest:checkWindowCustomView","testCaseName":"testpackage.WhenCustomViewTest","testSteps":[{"number":1,"description":"Открытие страницы","duration":25122,"startTime":"2023-06-20T09:36:02.291992+03:00[Europe/Moscow]","screenshots":[{"screenshot":"b33a2716edefc3d9446a69ab9978ff5d93c7843a6a630fbaf299c28aaeea7ad8.png","timeStamp":1687242962586},{"screenshot":"7c597f60ec8da9ce2f3f277569a1a6dea61338e11ebb484d05ffe66fa2819707.png","timeStamp":1687242987414}],"result":"SUCCESS","precondition":false,"level":0},{"number":2,"description":"Нажать кнопку","duration":763,"startTime":"2023-06-20T09:36:27.421561+03:00[Europe/Moscow]","screenshots":[{"screenshot":"89f60e25a45caa0d0e73c00065f5cc6ac67cc68aeddc3b642b710eb3e33fbb6f.png","timeStamp":1687242988184}],"result":"SUCCESS","precondition":false,"level":0},{"number":3,"description":"Ввод логина","duration":559,"startTime":"2023-06-20T09:36:28.187676+03:00[Europe/Moscow]","screenshots":[{"screenshot":"72759e3c84238ae0d269ce6a90184871fe6c78075aa014498c0513e6bc977086.png","timeStamp":1687242988747}],"result":"SUCCESS","precondition":false,"level":0},{"number":4,"description":"Ввод пароля","duration":559,"startTime":"2023-06-20T09:36:28.751569200+03:00[Europe/Moscow]","screenshots":[{"screenshot":"485ea428a497f8ef2eaff090e6e2f241a3015ef22aaafa78bd5a8f1b931cbe46.png","timeStamp":1687242989311}],"result":"SUCCESS","precondition":false,"level":0},{"number":5,"description":"Нажать кнопку","duration":5168,"startTime":"2023-06-20T09:36:29.313375100+03:00[Europe/Moscow]","screenshots":[{"screenshot":"42bcaa95134aa0ae1a74ad8a750b30353ce3b94a41512be1383fa17698fa78b1.png","timeStamp":1687242994480}],"result":"SUCCESS","precondition":false,"level":0},{"number":6,"description":"Нажать кнопку","duration":946,"startTime":"2023-06-20T09:36:34.483506600+03:00[Europe/Moscow]","screenshots":[{"screenshot":"542a52f1334762429b75969f78e03c216861c0dbb5c2d405a61e275c98025559.png","timeStamp":1687242995429}],"result":"SUCCESS","precondition":false,"level":0},{"number":7,"description":"Проверка списка пользовательских видов","duration":2230,"startTime":"2023-06-20T09:36:35.431994200+03:00[Europe/Moscow]","screenshots":[{"screenshot":"1e834da6cfef0513f60a8289d902107e36a30fc3f8e2f1e29ba59a70d097affe.png","timeStamp":1687242997662}],"result":"SUCCESS","precondition":false,"level":0},{"number":8,"description":"Ввести название пользовательского вида","duration":2484,"startTime":"2023-06-20T09:36:37.664411+03:00[Europe/Moscow]","screenshots":[{"screenshot":"1e834da6cfef0513f60a8289d902107e36a30fc3f8e2f1e29ba59a70d097affe.png","htmlSource":"pagesource14887633882690680263.html.txt","timeStamp":1687243000141}],"exception":{"errorType":"org.openqa.selenium.NoSuchElementException","message":"no such element: Unable to locate element: {\"method\":\"xpath\",\"selector\":\"//div[@id\u003d\u0027search-view-tabs\u0027]//input\"}\n  (Session info: chrome\u003d114.0.5735.110)\nFor documentation on this error, please visit: https://www.seleniumhq.org/exceptions/no_such_element.html\nBuild info: version: \u00273.141.59\u0027, revision: \u0027e82be7d358\u0027, time: \u00272018-11-14T08:17:03\u0027\nSystem info: host: \u0027DESKTOP-I8U9460\u0027, ip: \u0027192.168.1.143\u0027, os.name: \u0027Windows 10\u0027, os.arch: \u0027amd64\u0027, os.version: \u002710.0\u0027, java.version: \u002711.0.12\u0027\nDriver info: org.openqa.selenium.chrome.ChromeDriver\nCapabilities {acceptInsecureCerts: false, browserName: chrome, browserVersion: 114.0.5735.110, chrome: {chromedriverVersion: 114.0.5735.90 (386bc09e8f4f..., userDataDir: C:\\Users\\prog\\AppData\\Local...}, goog:chromeOptions: {debuggerAddress: localhost:54051}, javascriptEnabled: true, networkConnectionEnabled: false, pageLoadStrategy: normal, platform: WINDOWS, platformName: WINDOWS, proxy: Proxy(), setWindowRect: true, strictFileInteractability: false, timeouts: {implicit: 0, pageLoad: 300000, script: 30000}, unhandledPromptBehavior: dismiss and notify, webauthn:extension:credBlob: true, webauthn:extension:largeBlob: true, webauthn:extension:minPinLength: true, webauthn:extension:prf: true, webauthn:virtualAuthenticators: true}\nSession ID: 3a0d0a7a82d0fa3df69656534a587f9b\n*** Element info: {Using\u003dxpath, value\u003d//div[@id\u003d\u0027search-view-tabs\u0027]//input}","stackTrace":[{"declaringClass":"pages.CustomView","methodName":"typeNameCustomView","fileName":"CustomView.java","lineNumber":109},{"declaringClass":"steps.CustomViewSteps","methodName":"type_name_custom_view","fileName":"CustomViewSteps.java","lineNumber":54},{"declaringClass":"testpackage.WhenCustomViewTest","methodName":"checkWindowCustomView","fileName":"WhenCustomViewTest.java","lineNumber":197}]},"result":"ERROR","precondition":false,"level":0},{"number":9,"description":"Нажать кнопку","duration":2,"startTime":"2023-06-20T09:36:40.152237700+03:00[Europe/Moscow]","result":"SKIPPED","precondition":false,"level":0},{"number":10,"description":"Ожидание","duration":2,"startTime":"2023-06-20T09:36:40.156245500+03:00[Europe/Moscow]","result":"SKIPPED","precondition":false,"level":0},{"number":11,"description":"Проверка количества элементов в списке выбранных столбцов","duration":1,"startTime":"2023-06-20T09:36:40.160245600+03:00[Europe/Moscow]","result":"SKIPPED","precondition":false,"level":0},{"number":12,"description":"Проверка названия сохраненного пользовательского вида","duration":0,"startTime":"2023-06-20T09:36:40.162247+03:00[Europe/Moscow]","result":"SKIPPED","precondition":false,"level":0},{"number":13,"description":"Проверка кликабельности кнопки \"Сохранить настройки\" после сохранения пользовательского вида","duration":2,"startTime":"2023-06-20T09:36:40.173244600+03:00[Europe/Moscow]","result":"SKIPPED","precondition":false,"level":0},{"number":14,"description":"Нажать кнопку","duration":0,"startTime":"2023-06-20T09:36:40.176245500+03:00[Europe/Moscow]","result":"SKIPPED","precondition":false,"level":0},{"number":15,"description":"Нажать кнопку","duration":0,"startTime":"2023-06-20T09:36:40.179247700+03:00[Europe/Moscow]","result":"SKIPPED","precondition":false,"level":0},{"number":16,"description":"Проверка количества элементов в раскрывающемся списке пользовательских видов","duration":1,"startTime":"2023-06-20T09:36:40.181245700+03:00[Europe/Moscow]","result":"SKIPPED","precondition":false,"level":0},{"number":17,"description":"Проверка названия добавленного вида","duration":0,"startTime":"2023-06-20T09:36:40.183246300+03:00[Europe/Moscow]","result":"SKIPPED","precondition":false,"level":0},{"number":18,"description":"Нажать кнопку","duration":0,"startTime":"2023-06-20T09:36:40.185249300+03:00[Europe/Moscow]","result":"SKIPPED","precondition":false,"level":0},{"number":19,"description":"Нажать кнопку","duration":1,"startTime":"2023-06-20T09:36:40.187245+03:00[Europe/Moscow]","result":"SKIPPED","precondition":false,"level":0},{"number":20,"description":"Ввести название пользовательского вида","duration":1,"startTime":"2023-06-20T09:36:40.190249700+03:00[Europe/Moscow]","result":"SKIPPED","precondition":false,"level":0},{"number":21,"description":"Нажать кнопку","duration":1,"startTime":"2023-06-20T09:36:40.193248500+03:00[Europe/Moscow]","result":"SKIPPED","precondition":false,"level":0},{"number":22,"description":"Ожидание","duration":1,"startTime":"2023-06-20T09:36:40.197246400+03:00[Europe/Moscow]","result":"SKIPPED","precondition":false,"level":0},{"number":23,"description":"Проверка сообщения об ошибке при сохранении пользовательского вида при дублировании названия","duration":1,"startTime":"2023-06-20T09:36:40.199249300+03:00[Europe/Moscow]","result":"SKIPPED","precondition":false,"level":0},{"number":24,"description":"Проверка количества элементов в списке пользовательских видов","duration":0,"startTime":"2023-06-20T09:36:40.202247400+03:00[Europe/Moscow]","result":"SKIPPED","precondition":false,"level":0},{"number":25,"description":"Нажать кнопку","duration":1,"startTime":"2023-06-20T09:36:40.204248500+03:00[Europe/Moscow]","result":"SKIPPED","precondition":false,"level":0},{"number":26,"description":"Ввести название пользовательского вида","duration":0,"startTime":"2023-06-20T09:36:40.207253800+03:00[Europe/Moscow]","result":"SKIPPED","precondition":false,"level":0},{"number":27,"description":"Нажать кнопку","duration":0,"startTime":"2023-06-20T09:36:40.210251800+03:00[Europe/Moscow]","result":"SKIPPED","precondition":false,"level":0},{"number":28,"description":"Проверка сообщения об ошибке при сохранении пользовательского вида без выбранных столбцов","duration":1,"startTime":"2023-06-20T09:36:40.213247200+03:00[Europe/Moscow]","result":"SKIPPED","precondition":false,"level":0},{"number":29,"description":"Проверка количества элементов в списке выбранных столбцов","duration":0,"startTime":"2023-06-20T09:36:40.215249200+03:00[Europe/Moscow]","result":"SKIPPED","precondition":false,"level":0},{"number":30,"description":"Нажать кнопку","duration":0,"startTime":"2023-06-20T09:36:40.217250+03:00[Europe/Moscow]","result":"SKIPPED","precondition":false,"level":0},{"number":31,"description":"Нажать кнопку","duration":1,"startTime":"2023-06-20T09:36:40.218248300+03:00[Europe/Moscow]","result":"SKIPPED","precondition":false,"level":0},{"number":32,"description":"Проверка количества элементов в списке выбранных столбцов","duration":1,"startTime":"2023-06-20T09:36:40.220249400+03:00[Europe/Moscow]","result":"SKIPPED","precondition":false,"level":0}],"userStory":{"id":"testpackage.WhenCustomViewTest","storyName":"When custom view test","storyClassName":"testpackage.WhenCustomViewTest","path":"testpackage","type":"story"},"featureTag":{"name":"Testpackage/When custom view test","type":"story","displayName":"Testpackage/When custom view test"},"title":"Проверка окна пользовательского вида","tags":[{"name":"Testpackage/When custom view test","type":"story","displayName":"Testpackage/When custom view test"}],"startTime":"2023-06-20T09:35:56.904978500+03:00[Europe/Moscow]","duration":43480,"testFailureCause":{"errorType":"org.openqa.selenium.NoSuchElementException","message":"no such element: Unable to locate element: {\"method\":\"xpath\",\"selector\":\"//div[@id\u003d\u0027search-view-tabs\u0027]//input\"}\n  (Session info: chrome\u003d114.0.5735.110)\nFor documentation on this error, please visit: https://www.seleniumhq.org/exceptions/no_such_element.html\nBuild info: version: \u00273.141.59\u0027, revision: \u0027e82be7d358\u0027, time: \u00272018-11-14T08:17:03\u0027\nSystem info: host: \u0027DESKTOP-I8U9460\u0027, ip: \u0027192.168.1.143\u0027, os.name: \u0027Windows 10\u0027, os.arch: \u0027amd64\u0027, os.version: \u002710.0\u0027, java.version: \u002711.0.12\u0027\nDriver info: org.openqa.selenium.chrome.ChromeDriver\nCapabilities {acceptInsecureCerts: false, browserName: chrome, browserVersion: 114.0.5735.110, chrome: {chromedriverVersion: 114.0.5735.90 (386bc09e8f4f..., userDataDir: C:\\Users\\prog\\AppData\\Local...}, goog:chromeOptions: {debuggerAddress: localhost:54051}, javascriptEnabled: true, networkConnectionEnabled: false, pageLoadStrategy: normal, platform: WINDOWS, platformName: WINDOWS, proxy: Proxy(), setWindowRect: true, strictFileInteractability: false, timeouts: {implicit: 0, pageLoad: 300000, script: 30000}, unhandledPromptBehavior: dismiss and notify, webauthn:extension:credBlob: true, webauthn:extension:largeBlob: true, webauthn:extension:minPinLength: true, webauthn:extension:prf: true, webauthn:virtualAuthenticators: true}\nSession ID: 3a0d0a7a82d0fa3df69656534a587f9b\n*** Element info: {Using\u003dxpath, value\u003d//div[@id\u003d\u0027search-view-tabs\u0027]//input}\nFor documentation on this error, please visit: https://www.seleniumhq.org/exceptions/no_such_element.html\nBuild info: version: \u00273.141.59\u0027, revision: \u0027e82be7d358\u0027, time: \u00272018-11-14T08:17:03\u0027\nSystem info: host: \u0027DESKTOP-I8U9460\u0027, ip: \u0027192.168.1.143\u0027, os.name: \u0027Windows 10\u0027, os.arch: \u0027amd64\u0027, os.version: \u002710.0\u0027, java.version: \u002711.0.12\u0027\nDriver info: driver.version: unknown","stackTrace":[{"declaringClass":"pages.CustomView","methodName":"typeNameCustomView","fileName":"CustomView.java","lineNumber":109},{"declaringClass":"steps.CustomViewSteps","methodName":"type_name_custom_view","fileName":"CustomViewSteps.java","lineNumber":54},{"declaringClass":"testpackage.WhenCustomViewTest","methodName":"checkWindowCustomView","fileName":"WhenCustomViewTest.java","lineNumber":197}]},"testFailureClassname":"org.openqa.selenium.NoSuchElementException","testFailureMessage":"no such element: Unable to locate element: {\"method\":\"xpath\",\"selector\":\"//div[@id\u003d\u0027search-view-tabs\u0027]//input\"}\n  (Session info: chrome\u003d114.0.5735.110)\nFor documentation on this error, please visit: https://www.seleniumhq.org/exceptions/no_such_element.html\nBuild info: version: \u00273.141.59\u0027, revision: \u0027e82be7d358\u0027, time: \u00272018-11-14T08:17:03\u0027\nSystem info: host: \u0027DESKTOP-I8U9460\u0027, ip: \u0027192.168.1.143\u0027, os.name: \u0027Windows 10\u0027, os.arch: \u0027amd64\u0027, os.version: \u002710.0\u0027, java.version: \u002711.0.12\u0027\nDriver info: org.openqa.selenium.chrome.ChromeDriver\nCapabilities {acceptInsecureCerts: false, browserName: chrome, browserVersion: 114.0.5735.110, chrome: {chromedriverVersion: 114.0.5735.90 (386bc09e8f4f..., userDataDir: C:\\Users\\prog\\AppData\\Local...}, goog:chromeOptions: {debuggerAddress: localhost:54051}, javascriptEnabled: true, networkConnectionEnabled: false, pageLoadStrategy: normal, platform: WINDOWS, platformName: WINDOWS, proxy: Proxy(), setWindowRect: true, strictFileInteractability: false, timeouts: {implicit: 0, pageLoad: 300000, script: 30000}, unhandledPromptBehavior: dismiss and notify, webauthn:extension:credBlob: true, webauthn:extension:largeBlob: true, webauthn:extension:minPinLength: true, webauthn:extension:prf: true, webauthn:virtualAuthenticators: true}\nSession ID: 3a0d0a7a82d0fa3df69656534a587f9b\n*** Element info: {Using\u003dxpath, value\u003d//div[@id\u003d\u0027search-view-tabs\u0027]//input}\nFor documentation on this error, please visit: https://www.seleniumhq.org/exceptions/no_such_element.html\nBuild info: version: \u00273.141.59\u0027, revision: \u0027e82be7d358\u0027, time: \u00272018-11-14T08:17:03\u0027\nSystem info: host: \u0027DESKTOP-I8U9460\u0027, ip: \u0027192.168.1.143\u0027, os.name: \u0027Windows 10\u0027, os.arch: \u0027amd64\u0027, os.version: \u002710.0\u0027, java.version: \u002711.0.12\u0027\nDriver info: driver.version: unknown","testFailureSummary":"ERROR;org.openqa.selenium.NoSuchElementException;no such element: Unable to locate element: {\"method\":\"xpath\",\"selector\":\"//div[@id\u003d\u0027search-view-tabs\u0027]//input\"}\n  (Session info: chrome\u003d114.0.5735.110)\nFor documentation on this error, please visit: https://www.seleniumhq.org/exceptions/no_such_element.html\nBuild info: version: \u00273.141.59\u0027, revision: \u0027e82be7d358\u0027, time: \u00272018-11-14T08:17:03\u0027\nSystem info: host: \u0027DESKTOP-I8U9460\u0027, ip: \u0027192.168.1.143\u0027, os.name: \u0027Windows 10\u0027, os.arch: \u0027amd64\u0027, os.version: \u002710.0\u0027, java.version: \u002711.0.12\u0027\nDriver info: org.openqa.selenium.chrome.ChromeDriver\nCapabilities {acceptInsecureCerts: false, browserName: chrome, browserVersion: 114.0.5735.110, chrome: {chromedriverVersion: 114.0.5735.90 (386bc09e8f4f..., userDataDir: C:\\Users\\prog\\AppData\\Local...}, goog:chromeOptions: {debuggerAddress: localhost:54051}, javascriptEnabled: true, networkConnectionEnabled: false, pageLoadStrategy: normal, platform: WINDOWS, platformName: WINDOWS, proxy: Proxy(), setWindowRect: true, strictFileInteractability: false, timeouts: {implicit: 0, pageLoad: 300000, script: 30000}, unhandledPromptBehavior: dismiss and notify, webauthn:extension:credBlob: true, webauthn:extension:largeBlob: true, webauthn:extension:minPinLength: true, webauthn:extension:prf: true, webauthn:virtualAuthenticators: true}\nSession ID: 3a0d0a7a82d0fa3df69656534a587f9b\n*** Element info: {Using\u003dxpath, value\u003d//div[@id\u003d\u0027search-view-tabs\u0027]//input}\nFor documentation on this error, please visit: https://www.seleniumhq.org/exceptions/no_such_element.html\nBuild info: version: \u00273.141.59\u0027, revision: \u0027e82be7d358\u0027, time: \u00272018-11-14T08:17:03\u0027\nSystem info: host: \u0027DESKTOP-I8U9460\u0027, ip: \u0027192.168.1.143\u0027, os.name: \u0027Windows 10\u0027, os.arch: \u0027amd64\u0027, os.version: \u002710.0\u0027, java.version: \u002711.0.12\u0027\nDriver info: driver.version: unknown;CustomView.java","projectKey":"","annotatedResult":"ERROR","sessionId":"3a0d0a7a82d0fa3df69656534a587f9b","driver":"chrome","isManualTestingUpToDate":false,"manual":false,"testSource":"JUnit","order":0,"result":"ERROR"}