{"name":"checkClickableButtonCardView","id":"testpackage.TestCardView:checkClickableButtonCardView","testCaseName":"testpackage.TestCardView","testSteps":[{"number":1,"description":"Открытие страницы","duration":5657,"startTime":"2023-08-16T16:31:21.019255800+03:00[Europe/Moscow]","screenshots":[{"screenshot":"b8f294a4f5154dd86217d8584bfd90cc5860087a6ec03f14dd1f7d5ae1fc5da6.png","timeStamp":1692192681246},{"screenshot":"920accf5ded12bd4705e38cc281bf7281a3a5d6a22bd52a88f7ed0806fac4eb3.png","timeStamp":1692192686676}],"result":"SUCCESS","precondition":false,"level":0},{"number":2,"description":"Нажать кнопку","duration":711,"startTime":"2023-08-16T16:31:26.681576700+03:00[Europe/Moscow]","screenshots":[{"screenshot":"9ebdc244e359f2eb40667bf140ddebee70d3f773afbb21e5f3e686006ec717ea.png","timeStamp":1692192687393}],"result":"SUCCESS","precondition":false,"level":0},{"number":3,"description":"Ввод логина","duration":448,"startTime":"2023-08-16T16:31:27.394351200+03:00[Europe/Moscow]","screenshots":[{"screenshot":"62ed89b47a62590cb38fa7b08d2a6c3ea7810113636d0fc82c82a18dec3133c1.png","timeStamp":1692192687843}],"result":"SUCCESS","precondition":false,"level":0},{"number":4,"description":"Ввод пароля","duration":373,"startTime":"2023-08-16T16:31:27.845212100+03:00[Europe/Moscow]","screenshots":[{"screenshot":"e57dc30078ae6f3a716050aca9465e13da0eec5e1a1c9b22866e27f825e418b9.png","timeStamp":1692192688218}],"result":"SUCCESS","precondition":false,"level":0},{"number":5,"description":"Нажать кнопку","duration":1659,"startTime":"2023-08-16T16:31:28.219261300+03:00[Europe/Moscow]","screenshots":[{"screenshot":"09aeeee0f9bb2cbe17756dde8f388be2a8f7890c725473f8ce0ed3170dacf83e.png","timeStamp":1692192689877}],"result":"SUCCESS","precondition":false,"level":0},{"number":6,"description":"Проверка кликабельности кнопки \u0027Карточный вид\u0027","duration":515,"startTime":"2023-08-16T16:31:29.879520600+03:00[Europe/Moscow]","screenshots":[{"screenshot":"59b202a916f18f31c58b243e16dad9dc503d6ad13dbf95db67c04c1f6fe84b0a.png","timeStamp":1692192690395}],"result":"SUCCESS","precondition":false,"level":0}],"userStory":{"id":"testpackage.TestCardView","storyName":"Test card view","storyClassName":"testpackage.TestCardView","path":"testpackage","type":"story"},"featureTag":{"name":"Testpackage/Test card view","type":"story","displayName":"Testpackage/Test card view"},"title":"Проверка кликабельности кнопки \u0027Карточный вид\u0027","tags":[{"name":"Testpackage/Test card view","type":"story","displayName":"Testpackage/Test card view"}],"startTime":"2023-08-16T16:31:15.345153+03:00[Europe/Moscow]","duration":15054,"projectKey":"","sessionId":"9fbca207507054bf9f1170df9ca06e04","driver":"chrome","isManualTestingUpToDate":false,"manual":false,"testSource":"JUnit","order":0,"result":"SUCCESS"}