{"name":"checkNameWindowArbitrationCases","id":"testpackage.TestAuditor:checkNameWindowArbitrationCases","testCaseName":"testpackage.TestAuditor","testSteps":[{"number":1,"description":"Открытие страницы","duration":7137,"startTime":"2023-08-03T14:28:24.440686700+03:00[Europe/Moscow]","screenshots":[{"screenshot":"b33a2716edefc3d9446a69ab9978ff5d93c7843a6a630fbaf299c28aaeea7ad8.png","timeStamp":1691062104784},{"screenshot":"7c597f60ec8da9ce2f3f277569a1a6dea61338e11ebb484d05ffe66fa2819707.png","timeStamp":1691062111577}],"result":"SUCCESS","precondition":false,"level":0},{"number":2,"description":"Нажать кнопку","duration":1057,"startTime":"2023-08-03T14:28:31.585188100+03:00[Europe/Moscow]","screenshots":[{"screenshot":"08071e92a4ae93c517d3c3c589d8d6e59c2e22833cd09f7ac0d5d9e5057d67d4.png","timeStamp":1691062112641}],"result":"SUCCESS","precondition":false,"level":0},{"number":3,"description":"Ввод логина","duration":669,"startTime":"2023-08-03T14:28:32.644853900+03:00[Europe/Moscow]","screenshots":[{"screenshot":"282638f38829c59340634d0c87c6348af87baacddd639e5223e6046bf546afe3.png","timeStamp":1691062113314}],"result":"SUCCESS","precondition":false,"level":0},{"number":4,"description":"Ввод пароля","duration":626,"startTime":"2023-08-03T14:28:33.316680300+03:00[Europe/Moscow]","screenshots":[{"screenshot":"e1aebf07612aa658ca69f9a71f279b07c02575942be2ee243ee1f69fd9dd2c57.png","timeStamp":1691062113943}],"result":"SUCCESS","precondition":false,"level":0},{"number":5,"description":"Нажать кнопку","duration":2968,"startTime":"2023-08-03T14:28:33.945378+03:00[Europe/Moscow]","screenshots":[{"screenshot":"7a35d3a03fde6bf4cf48b1accc69203a88c08f89c4527d8cdb84818c5b02b18e.png","timeStamp":1691062116913}],"result":"SUCCESS","precondition":false,"level":0},{"number":6,"description":"Нажать кнопку","duration":1081,"startTime":"2023-08-03T14:28:36.916811600+03:00[Europe/Moscow]","screenshots":[{"screenshot":"0f2f07a4438787b3867aa363a83686142e04a88be95b60145e7104f817ee8c43.png","timeStamp":1691062117997}],"result":"SUCCESS","precondition":false,"level":0},{"number":7,"description":"Нажать кнопку","duration":2251,"startTime":"2023-08-03T14:28:37.999886+03:00[Europe/Moscow]","screenshots":[{"screenshot":"d7e2b217b9ecb194fd903339464177ca7ad53f1de42cc6b8424c17e871f838eb.png","timeStamp":1691062120251}],"result":"SUCCESS","precondition":false,"level":0},{"number":8,"description":"Ожидание","duration":724,"startTime":"2023-08-03T14:28:40.253462200+03:00[Europe/Moscow]","screenshots":[{"screenshot":"656000c7258837439116f43876dce990b6d6889c0a4195a757b2e1677452b161.png","timeStamp":1691062120978}],"result":"SUCCESS","precondition":false,"level":0},{"number":9,"description":"Перетаскивание фильтра","duration":646,"startTime":"2023-08-03T14:28:40.979157400+03:00[Europe/Moscow]","screenshots":[{"screenshot":"9ec7e2d7f506d602ed941f1c8dd31ee1cf9b4362371e3cf37edaa59988abf25f.png","timeStamp":1691062121624}],"result":"SUCCESS","precondition":false,"level":0},{"number":10,"description":"Ожидание","duration":702,"startTime":"2023-08-03T14:28:41.626943900+03:00[Europe/Moscow]","screenshots":[{"screenshot":"60279937b0db5ea6dd767d5361859994c05ebbe12eb7789f739ebf5d84ca2fda.png","timeStamp":1691062122329}],"result":"SUCCESS","precondition":false,"level":0},{"number":11,"description":"Ввод ключевого слова в поле \u0027включаем в поиск\u0027","duration":475,"startTime":"2023-08-03T14:28:42.331051100+03:00[Europe/Moscow]","screenshots":[{"screenshot":"665b4f9f94ebc6f7e0cc399fe514803348d09a1cf77b00ebcdf339cf7ad79b57.png","timeStamp":1691062122805}],"result":"SUCCESS","precondition":false,"level":0},{"number":12,"description":"Нажать кнопку","duration":526,"startTime":"2023-08-03T14:28:42.808371500+03:00[Europe/Moscow]","screenshots":[{"screenshot":"98bbb4bfc513242acdce6a514aa8444af6ffd884786c16857f6cbe2c3a95f462.png","timeStamp":1691062123335}],"result":"SUCCESS","precondition":false,"level":0},{"number":13,"description":"Нажать кнопку","duration":494,"startTime":"2023-08-03T14:28:43.338074300+03:00[Europe/Moscow]","screenshots":[{"screenshot":"ccbcc1a253c083e05eba09a7d0f5473d2ff05fde6aabc13fff307b349e9e00ca.png","timeStamp":1691062123832}],"result":"SUCCESS","precondition":false,"level":0},{"number":14,"description":"Ожидание","duration":697,"startTime":"2023-08-03T14:28:43.834568500+03:00[Europe/Moscow]","screenshots":[{"screenshot":"128dcb73ba270456875709015fb5bba9fd043072db116bbe41d4968a6a106032.png","timeStamp":1691062124532}],"result":"SUCCESS","precondition":false,"level":0},{"number":15,"description":"Нажать кнопку","duration":517,"startTime":"2023-08-03T14:28:44.533097300+03:00[Europe/Moscow]","screenshots":[{"screenshot":"92e30b6a99ccdc52bb7d4cecf1317808b464d2192ccf21c59c9752f64dc1343a.png","timeStamp":1691062125050}],"result":"SUCCESS","precondition":false,"level":0},{"number":16,"description":"Переключиться на следующую вкладку","duration":2595,"startTime":"2023-08-03T14:28:45.052637300+03:00[Europe/Moscow]","screenshots":[{"screenshot":"0f3b18fe1b7b76a5a35fbeb89d91cd3715b0da55a390aa7a72357be0ae7caf37.png","timeStamp":1691062127647}],"result":"SUCCESS","precondition":false,"level":0},{"number":17,"description":"Ожидание","duration":731,"startTime":"2023-08-03T14:28:47.649643400+03:00[Europe/Moscow]","screenshots":[{"screenshot":"abcaa28ab8d4dd8779c04f2c62d5a0d11a97c89f02bea29407b18dcf0d4cb2a4.png","timeStamp":1691062128381}],"result":"SUCCESS","precondition":false,"level":0},{"number":18,"description":"Нажать кнопку","duration":542,"startTime":"2023-08-03T14:28:48.382568100+03:00[Europe/Moscow]","screenshots":[{"screenshot":"baababde67b5e84c7016ab2b92a653df26db146795d7105b532bc4828c894725.png","timeStamp":1691062128924}],"result":"SUCCESS","precondition":false,"level":0},{"number":19,"description":"Нажать кнопку","duration":769,"startTime":"2023-08-03T14:28:48.926607500+03:00[Europe/Moscow]","screenshots":[{"screenshot":"b192e79d616c8c1778059c80133be23450699e2e70a6404a5983f490a369b226.png","timeStamp":1691062129696}],"result":"SUCCESS","precondition":false,"level":0},{"number":20,"description":"Проверка названия окна арбитражных дел","duration":393,"startTime":"2023-08-03T14:28:49.698204600+03:00[Europe/Moscow]","screenshots":[{"screenshot":"70e9826f4cd9d7a0e6f1913b459555de4ef9e028cbd0ff747222d0fb65cbf815.png","timeStamp":1691062130091}],"result":"SUCCESS","precondition":false,"level":0}],"userStory":{"id":"testpackage.TestAuditor","storyName":"Test auditor","storyClassName":"testpackage.TestAuditor","path":"testpackage","type":"story"},"featureTag":{"name":"Testpackage/Test auditor","type":"story","displayName":"Testpackage/Test auditor"},"title":"Проверка названия окна списка арбитражных дел","tags":[{"name":"Testpackage/Test auditor","type":"story","displayName":"Testpackage/Test auditor"}],"startTime":"2023-08-03T14:28:18.933596900+03:00[Europe/Moscow]","duration":31166,"projectKey":"","sessionId":"50298b1169eff99c5e1f74b0f97b882e","driver":"chrome","isManualTestingUpToDate":false,"manual":false,"testSource":"JUnit","order":0,"result":"SUCCESS"}